azure/mgmt/netapp/__init__.py
azure/mgmt/netapp/_client.py
azure/mgmt/netapp/_configuration.py
azure/mgmt/netapp/_patch.py
azure/mgmt/netapp/_validation.py
azure/mgmt/netapp/_version.py
azure/mgmt/netapp/py.typed
azure/mgmt/netapp/_utils/__init__.py
azure/mgmt/netapp/_utils/model_base.py
azure/mgmt/netapp/_utils/serialization.py
azure/mgmt/netapp/aio/__init__.py
azure/mgmt/netapp/aio/_client.py
azure/mgmt/netapp/aio/_configuration.py
azure/mgmt/netapp/aio/_patch.py
azure/mgmt/netapp/aio/operations/__init__.py
azure/mgmt/netapp/aio/operations/_operations.py
azure/mgmt/netapp/aio/operations/_patch.py
azure/mgmt/netapp/models/__init__.py
azure/mgmt/netapp/models/_enums.py
azure/mgmt/netapp/models/_models.py
azure/mgmt/netapp/models/_patch.py
azure/mgmt/netapp/operations/__init__.py
azure/mgmt/netapp/operations/_operations.py
azure/mgmt/netapp/operations/_patch.py
azure_mgmt_netapp-14.0.1.dist-info/licenses/LICENSE
azure_mgmt_netapp-14.0.1.dist-info/METADATA
azure_mgmt_netapp-14.0.1.dist-info/WHEEL
azure_mgmt_netapp-14.0.1.dist-info/top_level.txt
azure_mgmt_netapp-14.0.1.dist-info/RECORD
